<?xml version="1.0" encoding="UTF-8"?>
<con:testCase id="21059a19-7f23-4352-921d-0b07a7761ed5" discardOkResults="true" failOnError="true" failTestCaseOnErrors="true" keepSession="false" name="/TeeOff/v1/Reservation/ApplyPromoCode" searchProperties="true" timeout="0" xmlns:con="http://eviware.com/soapui/config"><con:settings><con:setting id="21059a19-7f23-4352-921d-0b07a7761ed5fileName">%2FTeeOff%2Fv1%2FReservation%2FApplyPromoCode</con:setting></con:settings><con:savedRecentRuns>1</con:savedRecentRuns><con:testStep type="restrequest" name="POST Request" id="aa3ddfea-1554-402d-b5b2-b1b942818b12"><con:settings/><con:config service="OpenTee.ExternalApi" resourcePath="/TeeOff/v1/Reservation/ApplyPromoCode" methodName="ReservationController_ApplyPromoCode" xsi:type="con:RestRequestStep" xmlns:xsi="http://www.w3.org/2001/XMLSchema-instance"><con:restRequest name="POST Request" id="02ca2fb7-551a-4e48-854c-e03504a2838c" mediaType="application/json" postQueryString="false"><con:settings><con:setting id="com.eviware.soapui.impl.wsdl.WsdlRequest@request-headers">&lt;xml-fragment/></con:setting></con:settings><con:endpoint>https://dev-api.opentee.com</con:endpoint><con:request>{"CourseId":0,"TeeTime":"2015-07-20T15:49:04-07:00","TeeTimeTypeId":0,"Price":1.23,"TransactionFee":1.23,"RegularPrice":1.23,"SavedAmount":1.23,"CancellationPeriod":0,"CurrencyLocaleId":0,"FeeId":0,"ReservationTypeId":0,"NumberOfPlayers":0,"OriginatingContactId":0,"Utilization":0,"Sku":"string","MinPlayers":0,"MaxPlayers":0,"AllowOne":true,"AllowTwo":true,"AllowThree":true,"AllowFour":true,"AllowFive":true,"ReservationString":"string"}</con:request><con:credentials><con:selectedAuthProfile>Inherit From Parent</con:selectedAuthProfile><con:authType>No Authorization</con:authType></con:credentials><con:jmsConfig JMSDeliveryMode="PERSISTENT"/><con:parameters/></con:restRequest></con:config></con:testStep><con:properties/><con:reportParameters/></con:testCase>