<?xml version="1.0" encoding="UTF-8"?>
<con:testCase id="ec5daad0-0560-4ac1-b065-47a060767a22" discardOkResults="true" failOnError="true" failTestCaseOnErrors="true" keepSession="false" name="/TeeOff/v1/User/GetUser" searchProperties="true" timeout="0" xmlns:con="http://eviware.com/soapui/config"><con:settings><con:setting id="ec5daad0-0560-4ac1-b065-47a060767a22fileName">%2FTeeOff%2Fv1%2FUser%2FGetUser</con:setting></con:settings><con:savedRecentRuns>1</con:savedRecentRuns><con:testStep type="restrequest" name="Test Request: Start Session" id="d70af070-47e1-4084-b474-14ac23b9379f"><con:settings/><con:config service="OpenTee.ExternalApi" resourcePath="/TeeOff/v1/User/SessionStart" methodName="UserController_SessionStart" xsi:type="con:RestRequestStep" xmlns:xsi="http://www.w3.org/2001/XMLSchema-instance"><con:restRequest name="Test Request: Start Session" id="2f40f6d9-87cd-492f-a23d-13d65b2dada5" mediaType="application/json" postQueryString="false"><con:settings><con:setting id="com.eviware.soapui.impl.wsdl.WsdlRequest@request-headers">&lt;xml-fragment/></con:setting></con:settings><con:endpoint>https://dev-api.opentee.com</con:endpoint><con:request/><con:originalUri>https://dev-api.opentee.com/TeeOff/v1/User/SessionStart</con:originalUri><con:assertion type="XPath Match" id="0c36140e-00a1-4e3a-9f17-397383888fd0" name="Success"><con:configuration><path>declare namespace ns1='https://dev-api.opentee.com/TeeOff/v1/User/SessionStart';
//ns1:Response[1]/ns1:Success[1]</path><content>true</content><allowWildcards>false</allowWildcards><ignoreNamspaceDifferences>false</ignoreNamspaceDifferences><ignoreComments>false</ignoreComments></con:configuration></con:assertion><con:credentials><con:selectedAuthProfile>Admin</con:selectedAuthProfile><con:authType>No Authorization</con:authType></con:credentials><con:jmsConfig JMSDeliveryMode="PERSISTENT"/><con:parameters/></con:restRequest></con:config></con:testStep><con:testStep type="restrequest" name="Test Request: Signin" id="d41f0235-799f-4b46-9417-a76108f6ebe4"><con:settings/><con:config service="OpenTee.ExternalApi" resourcePath="/TeeOff/v1/User/AuthenticateUser" methodName="UserController_AuthenticateUser" xsi:type="con:RestRequestStep" xmlns:xsi="http://www.w3.org/2001/XMLSchema-instance"><con:restRequest name="Test Request: Signin" id="f5821bb6-0f90-4979-ae50-9e52b61142e2" mediaType="application/json" postQueryString="false"><con:settings><con:setting id="com.eviware.soapui.impl.wsdl.WsdlRequest@request-headers">&lt;xml-fragment/></con:setting></con:settings><con:endpoint>https://dev-api.opentee.com</con:endpoint><con:request>{
   "UserName": "daisy@limesource.se",
   "Password": "limesource?01"
}</con:request><con:originalUri>https://dev-api.opentee.com/TeeOff/v1/User/AuthenticateUser</con:originalUri><con:assertion type="XPath Match" id="ba13efd8-9f79-4bbf-9972-b0d670f3aa42" name="ContactId is correct"><con:configuration><path>declare namespace ns1='https://dev-api.opentee.com/TeeOff/v1/User/AuthenticateUser';
//ns1:Response[1]/ns1:Data[1]/ns1:ContactId[1]</path><content>26571295</content><allowWildcards>false</allowWildcards><ignoreNamspaceDifferences>false</ignoreNamspaceDifferences><ignoreComments>false</ignoreComments></con:configuration></con:assertion><con:assertion type="XPath Match" id="500f1863-c692-4c43-b65c-0dcae192dae6" name="DateCreated is correct"><con:configuration><path>declare namespace ns1='https://dev-api.opentee.com/TeeOff/v1/User/AuthenticateUser';
//ns1:Response[1]/ns1:Data[1]/ns1:DateCreated[1]</path><content>5/12/2016 1:33:04 AM</content><allowWildcards>false</allowWildcards><ignoreNamspaceDifferences>false</ignoreNamspaceDifferences><ignoreComments>false</ignoreComments></con:configuration></con:assertion><con:assertion type="XPath Match" id="9af78b2e-cd47-46d0-ae54-a66e352ae1fc" name="Email is correct"><con:configuration><path>declare namespace ns1='https://dev-api.opentee.com/TeeOff/v1/User/AuthenticateUser';
//ns1:Response[1]/ns1:Data[1]/ns1:Email[1]</path><content>daisy@limesource.se</content><allowWildcards>false</allowWildcards><ignoreNamspaceDifferences>false</ignoreNamspaceDifferences><ignoreComments>false</ignoreComments></con:configuration></con:assertion><con:assertion type="XPath Match" id="dac113c8-3a98-47ce-9775-5914c2789bf8" name="UserName is correct"><con:configuration><path>declare namespace ns1='https://dev-api.opentee.com/TeeOff/v1/User/AuthenticateUser';
//ns1:Response[1]/ns1:Data[1]/ns1:Username[1]</path><content>daisyatim</content><allowWildcards>false</allowWildcards><ignoreNamspaceDifferences>false</ignoreNamspaceDifferences><ignoreComments>false</ignoreComments></con:configuration></con:assertion><con:credentials><con:username>daisy@limesource.se</con:username><con:password>limesource?01</con:password><con:selectedAuthProfile>Admin</con:selectedAuthProfile><con:authType>No Authorization</con:authType></con:credentials><con:jmsConfig JMSDeliveryMode="PERSISTENT"/><con:parameters><entry key="sessionId" value="${Test Request: Start Session#ResponseAsXml#declare namespace ns1='https://dev-api.opentee.com/TeeOff/v1/User/SessionStart'; //ns1:Response[1]/ns1:Data[1]}" xmlns="http://eviware.com/soapui/config"/></con:parameters></con:restRequest></con:config></con:testStep><con:testStep type="restrequest" name="Test Request: Get User" id="663b6a2b-fff0-4301-b7f5-c842563c5b88"><con:settings/><con:config service="OpenTee.ExternalApi" resourcePath="/TeeOff/v1/User/GetUser" methodName="UserController_GetUser" xsi:type="con:RestRequestStep" xmlns:xsi="http://www.w3.org/2001/XMLSchema-instance"><con:restRequest name="Test Request: Get User" id="ae12800a-6f40-467e-be4b-d00e84f77a32" mediaType="application/json"><con:settings><con:setting id="com.eviware.soapui.impl.wsdl.WsdlRequest@request-headers">&lt;xml-fragment/></con:setting></con:settings><con:endpoint>https://dev-api.opentee.com</con:endpoint><con:request/><con:originalUri>https://dev-api.opentee.com/TeeOff/v1/User/GetUser</con:originalUri><con:assertion type="XPath Match" id="af49e501-aa53-4b49-a5bf-fa0c7ac4e3ad" name="Username is correct."><con:configuration><path>declare namespace ns1='https://dev-api.opentee.com/TeeOff/v1/User/GetUser';
//ns1:Response[1]/ns1:Data[1]/ns1:Username[1]</path><content>daisyatim</content><allowWildcards>false</allowWildcards><ignoreNamspaceDifferences>false</ignoreNamspaceDifferences><ignoreComments>false</ignoreComments></con:configuration></con:assertion><con:assertion type="XPath Match" id="33b9541e-c3a2-4e5f-af28-234e7012ba18" name="DateCreated is correct."><con:configuration><path>declare namespace ns1='https://dev-api.opentee.com/TeeOff/v1/User/GetUser';
//ns1:Response[1]/ns1:Data[1]/ns1:DateCreated[1]</path><content>5/12/2016 1:33:04 AM</content><allowWildcards>false</allowWildcards><ignoreNamspaceDifferences>false</ignoreNamspaceDifferences><ignoreComments>false</ignoreComments></con:configuration></con:assertion><con:assertion type="XPath Match" id="5358f0da-e463-4712-a572-06ddad03c933" name="FirstName is correct."><con:configuration><path>declare namespace ns1='https://dev-api.opentee.com/TeeOff/v1/User/GetUser';
//ns1:Response[1]/ns1:Data[1]/ns1:FirstName[1]</path><content>Daisy</content><allowWildcards>false</allowWildcards><ignoreNamspaceDifferences>false</ignoreNamspaceDifferences><ignoreComments>false</ignoreComments></con:configuration></con:assertion><con:assertion type="XPath Match" id="05b43f69-c516-4451-af94-0afe752b8062" name="LastName is correct."><con:configuration><path>declare namespace ns1='https://dev-api.opentee.com/TeeOff/v1/User/GetUser';
//ns1:Response[1]/ns1:Data[1]/ns1:LastName[1]</path><content>Atim</content><allowWildcards>false</allowWildcards><ignoreNamspaceDifferences>false</ignoreNamspaceDifferences><ignoreComments>false</ignoreComments></con:configuration></con:assertion><con:assertion type="XPath Match" id="c213aeff-b87d-47c8-a09e-88e5ebe5beb4" name="ContactID is correct."><con:configuration><path>declare namespace ns1='https://dev-api.opentee.com/TeeOff/v1/User/GetUser';
//ns1:Response[1]/ns1:Data[1]/ns1:ContactId[1]</path><content>26571295</content><allowWildcards>false</allowWildcards><ignoreNamspaceDifferences>false</ignoreNamspaceDifferences><ignoreComments>false</ignoreComments></con:configuration></con:assertion><con:credentials><con:selectedAuthProfile>Inherit From Parent</con:selectedAuthProfile><con:authType>No Authorization</con:authType></con:credentials><con:jmsConfig JMSDeliveryMode="PERSISTENT"/><con:parameters>
  <con:entry key="contactId" value="${Test Request: Signin#ResponseAsXml#declare namespace ns1='https://dev-api.opentee.com/TeeOff/v1/User/AuthenticateUser'; //ns1:Response[1]/ns1:Data[1]/ns1:ContactId[1]}"/>
  <con:entry key="sessionId" value="${Test Request: Start Session#ResponseAsXml#declare namespace ns1='https://dev-api.opentee.com/TeeOff/v1/User/SessionStart'; //ns1:Response[1]/ns1:Data[1]}"/>
</con:parameters></con:restRequest></con:config></con:testStep><con:testStep type="restrequest" name="Test Request: Get User (Wrong ContactID)" id="3c7b757b-425f-40ad-bb1a-89939fbffb63"><con:settings/><con:config service="OpenTee.ExternalApi" resourcePath="/TeeOff/v1/User/GetUser" methodName="UserController_GetUser" xsi:type="con:RestRequestStep" xmlns:xsi="http://www.w3.org/2001/XMLSchema-instance"><con:restRequest name="Test Request: Get User (Wrong ContactID)" id="19001240-1938-40d4-a5f4-d857759f51f5" mediaType="application/json"><con:settings><con:setting id="com.eviware.soapui.impl.wsdl.WsdlRequest@request-headers">&lt;xml-fragment/></con:setting></con:settings><con:endpoint>https://dev-api.opentee.com</con:endpoint><con:request/><con:originalUri>https://dev-api.opentee.com/TeeOff/v1/User/GetUser</con:originalUri><con:assertion type="XPath Match" id="e3c0519d-eb24-4c54-8f74-68660b8ca38b" name="User has not been authenticated for the requested session."><con:configuration><path>declare namespace ns1='https://dev-api.opentee.com/TeeOff/v1/User/GetUser';
//ns1:Fault[1]/ns1:Message[1]</path><content>User has not been authenticated for the requested session.</content><allowWildcards>false</allowWildcards><ignoreNamspaceDifferences>false</ignoreNamspaceDifferences><ignoreComments>false</ignoreComments></con:configuration></con:assertion><con:credentials><con:selectedAuthProfile>Inherit From Parent</con:selectedAuthProfile><con:authType>No Authorization</con:authType></con:credentials><con:jmsConfig JMSDeliveryMode="PERSISTENT"/><con:parameters>
  <con:entry key="contactId" value="12121212"/>
  <con:entry key="sessionId" value="${Test Request: Start Session#ResponseAsXml#declare namespace ns1='https://dev-api.opentee.com/TeeOff/v1/User/SessionStart'; //ns1:Response[1]/ns1:Data[1]}"/>
</con:parameters></con:restRequest></con:config></con:testStep><con:testStep type="restrequest" name="Request: Get User (No ContactID Provided)" id="528acd60-24b4-4c30-b292-991953bd3dfb"><con:settings/><con:config service="OpenTee.ExternalApi" resourcePath="/TeeOff/v1/User/GetUser" methodName="UserController_GetUser" xsi:type="con:RestRequestStep" xmlns:xsi="http://www.w3.org/2001/XMLSchema-instance"><con:restRequest name="Request: Get User (No ContactID Provided)" id="19001240-1938-40d4-a5f4-d857759f51f5" mediaType="application/json"><con:settings><con:setting id="com.eviware.soapui.impl.wsdl.WsdlRequest@request-headers">&lt;xml-fragment/></con:setting></con:settings><con:endpoint>https://dev-api.opentee.com</con:endpoint><con:request/><con:originalUri>https://dev-api.opentee.com/TeeOff/v1/User/GetUser</con:originalUri><con:assertion type="XPath Match" id="e3c0519d-eb24-4c54-8f74-68660b8ca38b" name="The request is invalid."><con:configuration><path>declare namespace ns1='https://dev-api.opentee.com/TeeOff/v1/User/GetUser';
//ns1:Fault[1]/ns1:Message[1]</path><content>The request is invalid.</content><allowWildcards>false</allowWildcards><ignoreNamspaceDifferences>false</ignoreNamspaceDifferences><ignoreComments>false</ignoreComments></con:configuration></con:assertion><con:credentials><con:selectedAuthProfile>Inherit From Parent</con:selectedAuthProfile><con:authType>No Authorization</con:authType></con:credentials><con:jmsConfig JMSDeliveryMode="PERSISTENT"/><con:parameters><entry key="sessionId" value="${Test Request: Start Session#ResponseAsXml#declare namespace ns1='https://dev-api.opentee.com/TeeOff/v1/User/SessionStart'; //ns1:Response[1]/ns1:Data[1]}" xmlns="http://eviware.com/soapui/config"/></con:parameters></con:restRequest></con:config></con:testStep><con:properties/><con:reportParameters/><con:breakPoints><con:testStepId>9d957278-3787-4a0a-a9c2-03e8f4ec5946</con:testStepId><con:status>NONE</con:status><con:properties/></con:breakPoints><con:breakPoints><con:testStepId>d70af070-47e1-4084-b474-14ac23b9379f</con:testStepId><con:status>NONE</con:status><con:properties/></con:breakPoints><con:breakPoints><con:testStepId>d41f0235-799f-4b46-9417-a76108f6ebe4</con:testStepId><con:status>NONE</con:status><con:properties/></con:breakPoints></con:testCase>